{"hero":{"heroId":"777","name":"封魔剑魂","alias":"Yone","title":"永恩","roles":["assassin","fighter"],"shortBio":"生前，他是永恩，是亚索同母异父的哥哥，是故乡剑术道场的知名弟子。但当他死在弟弟手下以后，却发现自己被精神领域中的恶毒灵体所侵扰，不得不用它自己的刀剑将它弑杀。如今，被诅咒的永恩戴上了它的恶魔面具，开始了不懈的追猎，他要猎尽所有同种的恶魔，从而查清自己究竟成为了什么。","camp":"","campId":"","attack":"8","defense":"4","magic":"4","difficulty":"8","hp":"550.0000","hpperlevel":"85.0000","mp":"500.0000","mpperlevel":"0.0000","movespeed":"345.0000","armor":"28.0000","armorperlevel":"3.4000","spellblock":"32.0000","spellblockperlevel":"1.2500","attackrange":"175.0000","hpregen":"7.5000","hpregenperlevel":"0.7500","mpregen":"0.0000","mpregenperlevel":"0.0000","crit":"0.0000","critperlevel":"0.0000","attackdamage":"60.0000","attackdamageperlevel":"2.0000","attackspeed":"0.6250","attackspeedperlevel":"3.5000","allytips":["-"],"enemytips":["-"],"heroVideoPath":"","isWeekFree":"0","damageType":"kMixed","style":"5","difficultyL":"3","damage":"3","durability":"1","crowdControl":"2","mobility":"3","utility":"1","selectAudio":"https://game.gtimg.cn/images/lol/act/img/vo/choose/777.ogg","banAudio":"https://game.gtimg.cn/images/lol/act/img/vo/ban/777.ogg","changeLabel":"无改动","goldPrice":"6300","couponPrice":"4500","keywords":"永恩,封魔剑魂,ye,fmjh,Yone,yongen,fengmojianhun","introduce":"","palmHeroHeadImg":"https://game.gtimg.cn/images/lol/act/img/zmheropage/企业微信截图_16318055514972.png","relations":[]},"skins":[{"skinId":"777000","heroId":"777","heroName":"封魔剑魂","heroTitle":"永恩","name":"封魔剑魂","chromas":"0","chromasBelongId":"0","isBase":"1","emblemsName":"base","description":"","mainImg":"https://game.gtimg.cn/images/lol/act/img/skin/big777000.jpg","iconImg":"https://game.gtimg.cn/images/lol/act/img/skin/small777000.jpg","loadingImg":"https://game.gtimg.cn/images/lol/act/img/skinloading/777000.jpg","videoImg":"https://game.gtimg.cn/images/lol/act/img/skinvideo/sp777000.jpg","sourceImg":"https://game.gtimg.cn/images/lol/act/img/sourceImg/企业微信截图_16318055514972.png","vedioPath":"","suitType":"","publishTime":"","chromaImg":""},{"skinId":"777001","heroId":"777","heroName":"封魔剑魂","heroTitle":"永恩","name":"灵魂莲华 永恩","chromas":"0","chromasBelongId":"0","isBase":"0","emblemsName":"common","description":"很久以前，一对兄弟打了一场遍及艾欧尼亚的苦涩战争。兄弟中的哥哥，永恩，曾是一位大名，以坚守荣誉和职责而闻名。他为保卫国家和对抗那些破坏典礼和仪式的人而战——直到他被迫面对他那劣迹斑斑的亲弟弟。两人都注定要在最后的决斗中倒下……这或许就是对骄傲和狂妄的教训。","mainImg":"https://game.gtimg.cn/images/lol/act/img/skin/big777001.jpg","iconImg":"https://game.gtimg.cn/images/lol/act/img/skin/small777001.jpg","loadingImg":"https://game.gtimg.cn/images/lol/act/img/skinloading/777001.jpg","videoImg":"https://game.gtimg.cn/images/lol/act/img/skinvideo/sp777001.jpg","sourceImg":"https://game.gtimg.cn/images/lol/act/img/guidetop/guide777001.jpg","vedioPath":"","suitType":"","publishTime":"","chromaImg":""},{"skinId":"777002","heroId":"777","heroName":"封魔剑魂","heroTitle":"永恩","name":"灵魂莲华 永恩 流火之时","chromas":"1","chromasBelongId":"777001","isBase":"0","emblemsName":"","description":"","mainImg":"","iconImg":"","loadingImg":"","videoImg":"","sourceImg":"","vedioPath":"","suitType":"","publishTime":"","chromaImg":"https://game.gtimg.cn/images/lol/act/img/chromas/777/777002.png"},{"skinId":"777003","heroId":"777","heroName":"封魔剑魂","heroTitle":"永恩","name":"灵魂莲华 永恩 融冰之时","chromas":"1","chromasBelongId":"777001","isBase":"0","emblemsName":"","description":"","mainImg":"","iconImg":"","loadingImg":"","videoImg":"","sourceImg":"","vedioPath":"","suitType":"","publishTime":"","chromaImg":"https://game.gtimg.cn/images/lol/act/img/chromas/777/777003.png"},{"skinId":"777004","heroId":"777","heroName":"封魔剑魂","heroTitle":"永恩","name":"灵魂莲华 永恩 雁来之时","chromas":"1","chromasBelongId":"777001","isBase":"0","emblemsName":"","description":"","mainImg":"","iconImg":"","loadingImg":"","videoImg":"","sourceImg":"","vedioPath":"","suitType":"","publishTime":"","chromaImg":"https://game.gtimg.cn/images/lol/act/img/chromas/777/777004.png"},{"skinId":"777005","heroId":"777","heroName":"封魔剑魂","heroTitle":"永恩","name":"灵魂莲华 永恩 云开之时","chromas":"1","chromasBelongId":"777001","isBase":"0","emblemsName":"","description":"","mainImg":"","iconImg":"","loadingImg":"","videoImg":"","sourceImg":"","vedioPath":"","suitType":"","publishTime":"","chromaImg":"https://game.gtimg.cn/images/lol/act/img/chromas/777/777005.png"},{"skinId":"777006","heroId":"777","heroName":"封魔剑魂","heroTitle":"永恩","name":"灵魂莲华 永恩 春晓之时","chromas":"1","chromasBelongId":"777001","isBase":"0","emblemsName":"","description":"","mainImg":"","iconImg":"","loadingImg":"","videoImg":"","sourceImg":"","vedioPath":"","suitType":"","publishTime":"","chromaImg":"https://game.gtimg.cn/images/lol/act/img/chromas/777/777006.png"},{"skinId":"777007","heroId":"777","heroName":"封魔剑魂","heroTitle":"永恩","name":"灵魂莲华 永恩 星回之时","chromas":"1","chromasBelongId":"777001","isBase":"0","emblemsName":"","description":"","mainImg":"","iconImg":"","loadingImg":"","videoImg":"","sourceImg":"","vedioPath":"","suitType":"","publishTime":"","chromaImg":"https://game.gtimg.cn/images/lol/act/img/chromas/777/777007.png"},{"skinId":"777008","heroId":"777","heroName":"封魔剑魂","heroTitle":"永恩","name":"灵魂莲华 永恩 霜见之时","chromas":"1","chromasBelongId":"777001","isBase":"0","emblemsName":"","description":"","mainImg":"","iconImg":"","loadingImg":"","videoImg":"","sourceImg":"","vedioPath":"","suitType":"","publishTime":"","chromaImg":"https://game.gtimg.cn/images/lol/act/img/chromas/777/777008.png"},{"skinId":"777009","heroId":"777","heroName":"封魔剑魂","heroTitle":"永恩","name":"灵魂莲华 永恩 月升之时","chromas":"1","chromasBelongId":"777001","isBase":"0","emblemsName":"","description":"","mainImg":"","iconImg":"","loadingImg":"","videoImg":"","sourceImg":"","vedioPath":"","suitType":"","publishTime":"","chromaImg":"https://game.gtimg.cn/images/lol/act/img/chromas/777/777009.png"},{"skinId":"777010","heroId":"777","heroName":"封魔剑魂","heroTitle":"永恩","name":"战斗学院 永恩","chromas":"0","chromasBelongId":"0","isBase":"0","emblemsName":"common","description":"永恩是一名阴郁、安静的刺客俱乐部成员，他的孤僻和严肃的态度掩盖了他肩上的巨大创痕。 他和他弟弟之间的恩怨是众所周知的，即使是随便提起这事，也会引发永恩的怒火——凯特琳已经出于她自己的目的而注意到了这点。","mainImg":"https://game.gtimg.cn/images/lol/act/img/skin/big777010.jpg","iconImg":"https://game.gtimg.cn/images/lol/act/img/skin/small777010.jpg","loadingImg":"https://game.gtimg.cn/images/lol/act/img/skinloading/777010.jpg","videoImg":"https://game.gtimg.cn/images/lol/act/img/skinvideo/sp777010.jpg","sourceImg":"https://game.gtimg.cn/images/lol/act/img/guidetop/guide777010.jpg","vedioPath":"","suitType":"","publishTime":"","chromaImg":""},{"skinId":"777011","heroId":"777","heroName":"封魔剑魂","heroTitle":"永恩","name":"战斗学院 永恩 不死鸟","chromas":"1","chromasBelongId":"777010","isBase":"0","emblemsName":"","description":"","mainImg":"","iconImg":"","loadingImg":"","videoImg":"","sourceImg":"","vedioPath":"","suitType":"","publishTime":"","chromaImg":"https://game.gtimg.cn/images/lol/act/img/chromas/777/777011.png"},{"skinId":"777012","heroId":"777","heroName":"封魔剑魂","heroTitle":"永恩","name":"战斗学院 永恩 黑龙","chromas":"1","chromasBelongId":"777010","isBase":"0","emblemsName":"","description":"","mainImg":"","iconImg":"","loadingImg":"","videoImg":"","sourceImg":"","vedioPath":"","suitType":"","publishTime":"","chromaImg":"https://game.gtimg.cn/images/lol/act/img/chromas/777/777012.png"},{"skinId":"777013","heroId":"777","heroName":"封魔剑魂","heroTitle":"永恩","name":"战斗学院 永恩 火蜥蜴","chromas":"1","chromasBelongId":"777010","isBase":"0","emblemsName":"","description":"","mainImg":"","iconImg":"","loadingImg":"","videoImg":"","sourceImg":"","vedioPath":"","suitType":"","publishTime":"","chromaImg":"https://game.gtimg.cn/images/lol/act/img/chromas/777/777013.png"},{"skinId":"777014","heroId":"777","heroName":"封魔剑魂","heroTitle":"永恩","name":"战斗学院 永恩 夜枭","chromas":"1","chromasBelongId":"777010","isBase":"0","emblemsName":"","description":"","mainImg":"","iconImg":"","loadingImg":"","videoImg":"","sourceImg":"","vedioPath":"","suitType":"","publishTime":"","chromaImg":"https://game.gtimg.cn/images/lol/act/img/chromas/777/777014.png"},{"skinId":"777015","heroId":"777","heroName":"封魔剑魂","heroTitle":"永恩","name":"战斗学院 永恩 美人鱼","chromas":"1","chromasBelongId":"777010","isBase":"0","emblemsName":"","description":"","mainImg":"","iconImg":"","loadingImg":"","videoImg":"","sourceImg":"","vedioPath":"","suitType":"","publishTime":"","chromaImg":"https://game.gtimg.cn/images/lol/act/img/chromas/777/777015.png"},{"skinId":"777016","heroId":"777","heroName":"封魔剑魂","heroTitle":"永恩","name":"战斗学院 永恩 天马","chromas":"1","chromasBelongId":"777010","isBase":"0","emblemsName":"","description":"","mainImg":"","iconImg":"","loadingImg":"","videoImg":"","sourceImg":"","vedioPath":"","suitType":"","publishTime":"","chromaImg":"https://game.gtimg.cn/images/lol/act/img/chromas/777/777016.png"},{"skinId":"777017","heroId":"777","heroName":"封魔剑魂","heroTitle":"永恩","name":"战斗学院 永恩 森林龙","chromas":"1","chromasBelongId":"777010","isBase":"0","emblemsName":"","description":"","mainImg":"","iconImg":"","loadingImg":"","videoImg":"","sourceImg":"","vedioPath":"","suitType":"","publishTime":"","chromaImg":"https://game.gtimg.cn/images/lol/act/img/chromas/777/777017.png"},{"skinId":"777018","heroId":"777","heroName":"封魔剑魂","heroTitle":"永恩","name":"战斗学院 永恩 狮鹫","chromas":"1","chromasBelongId":"777010","isBase":"0","emblemsName":"","description":"","mainImg":"","iconImg":"","loadingImg":"","videoImg":"","sourceImg":"","vedioPath":"","suitType":"","publishTime":"","chromaImg":"https://game.gtimg.cn/images/lol/act/img/chromas/777/777018.png"},{"skinId":"777019","heroId":"777","heroName":"封魔剑魂","heroTitle":"永恩","name":"黎明使者 永恩","chromas":"0","chromasBelongId":"0","isBase":"0","emblemsName":"Legend","description":"预言表明众神将相互毁灭，迎来创造本身的终结——但永恩决心挑战命运。 作为在混沌与秩序之间的冲突中诞生的半人半神，永恩拥有黑夜和黎明的力量。 他必须团结他的同胞们，将和平带给众神……否则他们都会灭亡。","mainImg":"https://game.gtimg.cn/images/lol/act/img/skin/big777019.jpg","iconImg":"https://game.gtimg.cn/images/lol/act/img/skin/small777019.jpg","loadingImg":"https://game.gtimg.cn/images/lol/act/img/skinloading/777019.jpg","videoImg":"https://game.gtimg.cn/images/lol/act/img/skinvideo/sp777019.jpg","sourceImg":"https://game.gtimg.cn/images/lol/act/img/guidetop/guide777019.jpg","vedioPath":"","suitType":"","publishTime":"","chromaImg":""},{"skinId":"777020","heroId":"777","heroName":"封魔剑魂","heroTitle":"永恩","name":"黎明使者 永恩 阳辉","chromas":"1","chromasBelongId":"777019","isBase":"0","emblemsName":"","description":"","mainImg":"","iconImg":"","loadingImg":"","videoImg":"","sourceImg":"","vedioPath":"","suitType":"","publishTime":"","chromaImg":"https://game.gtimg.cn/images/lol/act/img/chromas/777/777020.png"},{"skinId":"777021","heroId":"777","heroName":"封魔剑魂","heroTitle":"永恩","name":"黎明使者 永恩 宁辉","chromas":"1","chromasBelongId":"777019","isBase":"0","emblemsName":"","description":"","mainImg":"","iconImg":"","loadingImg":"","videoImg":"","sourceImg":"","vedioPath":"","suitType":"","publishTime":"","chromaImg":"https://game.gtimg.cn/images/lol/act/img/chromas/777/777021.png"},{"skinId":"777022","heroId":"777","heroName":"封魔剑魂","heroTitle":"永恩","name":"黎明使者 永恩 霞辉","chromas":"1","chromasBelongId":"777019","isBase":"0","emblemsName":"","description":"","mainImg":"","iconImg":"","loadingImg":"","videoImg":"","sourceImg":"","vedioPath":"","suitType":"","publishTime":"","chromaImg":"https://game.gtimg.cn/images/lol/act/img/chromas/777/777022.png"},{"skinId":"777023","heroId":"777","heroName":"封魔剑魂","heroTitle":"永恩","name":"黎明使者 永恩 雪辉","chromas":"1","chromasBelongId":"777019","isBase":"0","emblemsName":"","description":"","mainImg":"","iconImg":"","loadingImg":"","videoImg":"","sourceImg":"","vedioPath":"","suitType":"","publishTime":"","chromaImg":"https://game.gtimg.cn/images/lol/act/img/chromas/777/777023.png"},{"skinId":"777024","heroId":"777","heroName":"封魔剑魂","heroTitle":"永恩","name":"黎明使者 永恩 苍辉","chromas":"1","chromasBelongId":"777019","isBase":"0","emblemsName":"","description":"","mainImg":"","iconImg":"","loadingImg":"","videoImg":"","sourceImg":"","vedioPath":"","suitType":"","publishTime":"","chromaImg":"https://game.gtimg.cn/images/lol/act/img/chromas/777/777024.png"},{"skinId":"777025","heroId":"777","heroName":"封魔剑魂","heroTitle":"永恩","name":"黎明使者 永恩 生辉","chromas":"1","chromasBelongId":"777019","isBase":"0","emblemsName":"","description":"","mainImg":"","iconImg":"","loadingImg":"","videoImg":"","sourceImg":"","vedioPath":"","suitType":"","publishTime":"","chromaImg":"https://game.gtimg.cn/images/lol/act/img/chromas/777/777025.png"}],"spells":[{"heroId":"777","spellKey":"e","name":"破障之锋","description":"永恩进入灵体形态5秒，期间会将身体留在原地，并获得10%不断提升的移动速度。\n当灵体形态结束时，永恩会返回他的身体，并再次造成伤害，伤害值相当于他在此期间对英雄造成伤害的(25%/27.5%/30%/32.5%/35%)\n再次施放：提前结束灵体形态。\n在此期间，移动速度会从10%不断提升至30%。","abilityIconPath":"https://game.gtimg.cn/images/lol/act/img/spell/YoneE.png","abilityVideoPath":"champion-abilities/0777/ability_0777_E1.webm","dynamicDescription":"","cost":["0"],"costburn":"0","cooldown":["0"],"cooldownburn":"22/19/16/13/10","range":["0"]},{"heroId":"777","spellKey":"passive","name":"狩人之道","description":"永恩手持双剑，所以他的每第二次攻击可造成50%魔法伤害、\n永恩的暴击几率提升150%，但暴击伤害会降低10%。\n这个效果的计算顺序处在所有其它的暴击几率修正效果之后。\n额外暴击几率转化为攻击力的转化比：每1%暴击几率转化为0.4攻击力","abilityIconPath":"https://game.gtimg.cn/images/lol/act/img/passive/YonePassive.Yone.png","abilityVideoPath":"champion-abilities/0777/ability_0777_P1.webm","dynamicDescription":"","cost":false,"costburn":"","cooldown":false,"cooldownburn":"","range":false},{"heroId":"777","spellKey":"q","name":"错玉切","description":"永恩向前出剑，造成(20/40/60/80/100 +105%AD)物理伤害。在命中时，错玉切回获得一层可叠加的效果，持续6秒。在积攒2层效果后，错玉切会使永恩向前冲刺，并带着一阵能够击飞敌人0.75秒的旋风，造成(20 +100%AD)物理伤害。\n这个技能可以暴击，施加攻击特效，会被控制技能打断，并且它的冷却时间和施放时间可通过攻击速度来缩短。","abilityIconPath":"https://game.gtimg.cn/images/lol/act/img/spell/YoneQ.png","abilityVideoPath":"champion-abilities/0777/ability_0777_Q1.webm","dynamicDescription":"","cost":["0"],"costburn":"0","cooldown":["0"],"cooldownburn":"4","range":["0"]},{"heroId":"777","spellKey":"r","name":"封尘绝念斩","description":"永恩对一条路径上的所有敌人进行打击，造成(100/200/300 +40%AD)物理伤害和(100/200/300 +40%AD)魔法伤害，传送至命中的最后一名敌方英雄身后，并将命中的所有敌人击飞向永恩。\n如果没有命中任何敌方英雄，那么永恩将闪烁至技能的最大距离处。","abilityIconPath":"https://game.gtimg.cn/images/lol/act/img/spell/YoneR.png","abilityVideoPath":"champion-abilities/0777/ability_0777_R1.webm","dynamicDescription":"","cost":["0"],"costburn":"0","cooldown":["0"],"cooldownburn":"120/100/80","range":["0"]},{"heroId":"777","spellKey":"w","name":"凛神斩","description":"永恩向前顺劈，造成(5/10/15/20/25)+目标(5.5%/6%/6.5%/7%/7.5%)最大生命值的物理伤害和目标(5.5%/6%/6.5%/7%/7.5%)最大生命值的魔法伤害。\n如果永恩命中了敌方单位，那么他会获得(40-60 +60%额外AD)护盾，持续1.5秒。每命中一名敌方英雄，护盾生命值都会提升。\n命中的首个敌方英雄会使护盾生命值提升100%，命中的所有后续敌方英雄都会使护盾生命值提升50%。\n这个技能的冷却时间和施放时间可通过 攻击速度来缩短。\n对小兵的最小总伤害值为(40-410)。","abilityIconPath":"https://game.gtimg.cn/images/lol/act/img/spell/YoneW.png","abilityVideoPath":"champion-abilities/0777/ability_0777_W1.webm","dynamicDescription":"","cost":["0"],"costburn":"0","cooldown":["0"],"cooldownburn":"16","range":["0"]}],"version":"12.5","fileName":"777.js","fileTime":"2022-03-10 15:01:43"}
